gpder/__init__.py
gpder/bayes/__init__.py
gpder/bayes/bayes_opt.py
gpder/gaussian_process/__init__.py
gpder/gaussian_process/gaussian_process.py
gpder/gaussian_process/kernels/__init__.py
gpder/gaussian_process/kernels/derivative.py
gpder/gaussian_process/kernels/regular.py
gpder-1.0.0.dist-info/METADATA
gpder-1.0.0.dist-info/WHEEL
gpder-1.0.0.dist-info/licenses/LICENSE
gpder-1.0.0.dist-info/RECORD
