Metadata-Version: 2.3
Name: gpder
Version: 1.0.0
Summary: Bayesian Experimental Design for Minimizing the Uncertainty of Gaussian Processes
Project-URL: Homepage, https://github.com/alexxromero/gpder
Project-URL: Issues, https://github.com/alexxromero/gpder/issues
Author-email: Alexis Romero <alexir2@uci.edu>
License-File: LICENSE
Classifier: License :: OSI Approved :: MIT License
Classifier: Operating System :: OS Independent
Classifier: Programming Language :: Python :: 3
Requires-Python: >=3.6
Requires-Dist: numpy
Requires-Dist: scikit-learn
Requires-Dist: scipy
